ProxyGuysPy
