Metadata-Version: 1.0
Name: ProxyGuysPy
Version: 1.1
Summary: Python API for ProxyGuys
Home-page: UNKNOWN
Author: Kurt Kobzeff
Author-email: UNKNOWN
License: UNKNOWN
Platform: UNKNOWN
